scrapy_splitvariants/__init__.py
scrapy_splitvariants/middleware.py
scrapy_splitvariants-1.1.0.dist-info/DESCRIPTION.rst
scrapy_splitvariants-1.1.0.dist-info/METADATA
scrapy_splitvariants-1.1.0.dist-info/RECORD
scrapy_splitvariants-1.1.0.dist-info/WHEEL
scrapy_splitvariants-1.1.0.dist-info/metadata.json
scrapy_splitvariants-1.1.0.dist-info/top_level.txt
